setup.py
faamtools/__init__.py
faamtools/avaps.py
faamtools/cloud.py
faamtools/core.py
faamtools/utils.py
faamtools/version.py
faamtools.egg-info/PKG-INFO
faamtools.egg-info/SOURCES.txt
faamtools.egg-info/dependency_links.txt
faamtools.egg-info/pbr.json
faamtools.egg-info/top_level.txt