Metadata-Version: 1.1
Name: faamtools
Version: 0.2.3
Summary: faamtools: a Python toolbox to read FAAM data
Home-page: http://github.com/dennissergeev/faamtools
Author: Denis Sergeev
Author-email: dennis.sergeev@gmail.com
License: MIT
Platform: UNKNOWN
Classifier: Development Status :: 3 - Alpha
Classifier: Environment :: Console
Classifier: Intended Audience :: Science/Research
Classifier: License :: OSI Approved :: MIT License
Classifier: Operating System :: POSIX :: Linux
Classifier: Programming Language :: Python
Classifier: Topic :: Scientific/Engineering :: Atmospheric Science
Requires: h5py
Requires: netcdf4
Requires: numpy
